{"name":"Rabbit","tagline":"An EE library that simplifies multiple forms of authentication","body":"Rabbit\r\n======\r\n\r\nSupporting ArmorGames, Kongregate, MouseBreaker, Facebook, username and email authentication mechanisms Rabbit allows [Everybody Edits](http://everybodyedits.com) developers to seamlessly integrate many forms of authentication in one interface. Rabbit detects the type of input and authenticates users to the appropriate service.\r\n\r\nTo use Rabbit, type:\r\n\r\n```csharp\r\nvar conn = RabbitAuth.LogIn (EmailOrTokenOrUserName, RoomID, Password = null);\r\n```\r\n\r\n_The password parameter is optional if Facebook authentication is used._\r\n\r\nUsing NuGet? Just download the [EE-Rabbit](http://www.nuget.org/packages/EE-Rabbit/) package.\r\n\r\n\r\nRabbit icon by https://flic.kr/p/cVkan9","google":"UA-53239844-1","note":"Don't delete this file! It's used internally to help with page regeneration."}